{
  "lunch1": {
    "pizzaId": "pizza1",
    "employeeId": "employee2",
    "date": "2019-10-26"
  },
  "lunch2": {
    "pizzaId": "pizza2",
    "employeeId": "employee3",
    "date": "2019-10-24"
  },
  "lunch3": {
    "pizzaId": "pizza3",
    "employeeId": "employee4",
    "date": "2019-10-22"
  },
  "lunch4": {
    "pizzaId": "pizza4",
    "employeeId": "employee5",
    "date": "2019-10-20"
  },
  "lunch5": {
    "pizzaId": "pizza5",
    "employeeId": "employee6",
    "date": "2019-10-23"
  }
}